kocher_tools/__init__.py
kocher_tools/alignment.py
kocher_tools/assignment.py
kocher_tools/backup.py
kocher_tools/barcode.py
kocher_tools/barcode_filter.py
kocher_tools/barcode_pipeline.py
kocher_tools/blast.py
kocher_tools/calc_MK.py
kocher_tools/calc_fst.py
kocher_tools/calc_pbs.py
kocher_tools/calc_pca.py
kocher_tools/collection.py
kocher_tools/common.py
kocher_tools/compress.py
kocher_tools/config_file.py
kocher_tools/create_database.py
kocher_tools/database.py
kocher_tools/deML.py
kocher_tools/demultiplex_paired_barcodes.py
kocher_tools/demultiplex_pipeline.py
kocher_tools/fastq_multx.py
kocher_tools/featureCounts_report.py
kocher_tools/gff.py
kocher_tools/gff_add_features.py
kocher_tools/gff_chrom_stats.py
kocher_tools/gff_position_stats.py
kocher_tools/insert_file.py
kocher_tools/kocher_database.py
kocher_tools/location.py
kocher_tools/logger.py
kocher_tools/mafft.py
kocher_tools/misc.py
kocher_tools/model.py
kocher_tools/multiplex.py
kocher_tools/nstats.py
kocher_tools/output.py
kocher_tools/plink2.py
kocher_tools/retrieve_samples.py
kocher_tools/softmask.py
kocher_tools/storage.py
kocher_tools/upload_samples.py
kocher_tools/vsearch.py
kocher_tools/data/i7_map.txt
kocher_tools-0.1.50.data/scripts/barcode_filter.py
kocher_tools-0.1.50.data/scripts/barcode_pipeline.py
kocher_tools-0.1.50.data/scripts/calc_MK.py
kocher_tools-0.1.50.data/scripts/calc_fst.py
kocher_tools-0.1.50.data/scripts/calc_pbs.py
kocher_tools-0.1.50.data/scripts/calc_pca.py
kocher_tools-0.1.50.data/scripts/create_database.py
kocher_tools-0.1.50.data/scripts/demultiplex_paired_barcodes.py
kocher_tools-0.1.50.data/scripts/demultiplex_pipeline.py
kocher_tools-0.1.50.data/scripts/featureCounts_report.py
kocher_tools-0.1.50.data/scripts/gff_add_features.py
kocher_tools-0.1.50.data/scripts/gff_chrom_stats.py
kocher_tools-0.1.50.data/scripts/gff_position_stats.py
kocher_tools-0.1.50.data/scripts/insert_file.py
kocher_tools-0.1.50.data/scripts/softmask.py
kocher_tools-0.1.50.dist-info/METADATA
kocher_tools-0.1.50.dist-info/WHEEL
kocher_tools-0.1.50.dist-info/top_level.txt
kocher_tools-0.1.50.dist-info/RECORD
